matchenc/__init__.py
matchenc/__main__.py
matchenc-1.1.dist-info/LICENSE
matchenc-1.1.dist-info/METADATA
matchenc-1.1.dist-info/WHEEL
matchenc-1.1.dist-info/top_level.txt
matchenc-1.1.dist-info/RECORD
