Metadata-Version: 2.1
Name: matchenc
Version: 1.1
Summary: Checks which standard encoding can open the given file, and if contains the expected terms are encoded as such.
Home-page: https://github.com/gythaogg/matchenc
Author: Gytha Ogg
Author-email: gythaoggscat@gmail.com
License: MIT
Keywords: Standard Encoding Decoding
Platform: UNKNOWN
Classifier: Development Status :: 5 - Production/Stable
Classifier: License :: OSI Approved :: MIT License
Classifier: Programming Language :: Python :: 3.6
Classifier: Topic :: Scientific/Engineering :: Information Analysis
Requires-Dist: markdown
